hexa_mlops/__init__.py
hexa_mlops/cli.py
hexa_mlops/acs/__init__.py
hexa_mlops/acs/ml_deploy_helm_value_generator.py
hexa_mlops/azureml/__init__.py
hexa_mlops/azureml/azure_data_asset_register_generator.py
hexa_mlops/azureml/azure_datastore_register_generator.py
hexa_mlops/azureml/azure_inference_deployment_file_generator.py
hexa_mlops/azureml/azure_pipeline_file_generator.py
hexa_mlops/azureml/azure_training_batch_deployment_file_generator.py
hexa_mlops/azureml/conda_file_generator.py
hexa_mlops/azureml/env_file_generator.py
hexa_mlops/base/__init__.py
hexa_mlops/base/constants.py
hexa_mlops/base/file_generator.py
hexa_mlops/utils/__init__.py
hexa_mlops/utils/acs_utils.py
hexa_mlops-0.2.1.dist-info/licenses/LICENSE
hexa_mlops-0.2.1.dist-info/METADATA
hexa_mlops-0.2.1.dist-info/WHEEL
hexa_mlops-0.2.1.dist-info/entry_points.txt
hexa_mlops-0.2.1.dist-info/top_level.txt
hexa_mlops-0.2.1.dist-info/RECORD
