Metadata-Version: 2.4
Name: hexa_mlops
Version: 0.2.1
Summary: Hexa MLOps package
Author: Thi Thuy Duyen Pham, Liam Mulhall
Author-email: irene.d.pham@gmail.com, lmulhall@amadeus.com
License-File: LICENSE
Requires-Dist: pyyaml
Requires-Dist: python-dotenv
Requires-Dist: Jinja2
Dynamic: author
Dynamic: author-email
Dynamic: description
Dynamic: description-content-type
Dynamic: license-file
Dynamic: requires-dist
Dynamic: summary
